odoo/addons/fs_product_public_category_multi_image/README.rst
odoo/addons/fs_product_public_category_multi_image/__init__.py
odoo/addons/fs_product_public_category_multi_image/__manifest__.py
odoo/addons/fs_product_public_category_multi_image/i18n/fs_product_public_category_multi_image.pot
odoo/addons/fs_product_public_category_multi_image/i18n/it.po
odoo/addons/fs_product_public_category_multi_image/models/__init__.py
odoo/addons/fs_product_public_category_multi_image/models/fs_product_public_category_image.py
odoo/addons/fs_product_public_category_multi_image/models/image_tag.py
odoo/addons/fs_product_public_category_multi_image/models/product_public_category.py
odoo/addons/fs_product_public_category_multi_image/readme/CONTRIBUTORS.rst
odoo/addons/fs_product_public_category_multi_image/readme/DESCRIPTION.rst
odoo/addons/fs_product_public_category_multi_image/readme/USAGE.rst
odoo/addons/fs_product_public_category_multi_image/security/fs_product_public_category_image.xml
odoo/addons/fs_product_public_category_multi_image/static/description/icon.png
odoo/addons/fs_product_public_category_multi_image/static/description/index.html
odoo/addons/fs_product_public_category_multi_image/tests/__init__.py
odoo/addons/fs_product_public_category_multi_image/tests/test_fs_product_multi_image.py
odoo/addons/fs_product_public_category_multi_image/views/fs_product_public_category_image.xml
odoo/addons/fs_product_public_category_multi_image/views/product_public_category.xml
odoo_addon_fs_product_public_category_multi_image-16.0.1.0.0.4.dist-info/METADATA
odoo_addon_fs_product_public_category_multi_image-16.0.1.0.0.4.dist-info/WHEEL
odoo_addon_fs_product_public_category_multi_image-16.0.1.0.0.4.dist-info/top_level.txt
odoo_addon_fs_product_public_category_multi_image-16.0.1.0.0.4.dist-info/RECORD
