Metadata-Version: 2.1
Name: odoo-addon-fs_product_public_category_multi_image
Version: 16.0.1.0.0.4
Summary: Manage multi images from extenal file system on eCommerce public categories
Home-page: https://github.com/OCA/storage
Author: Odoo Community Association (OCA)
Author-email: support@odoo-community.org
License: AGPL-3
Classifier: Programming Language :: Python
Classifier: Framework :: Odoo
Classifier: Framework :: Odoo :: 16.0
Classifier: License :: OSI Approved :: GNU Affero General Public License v3
Classifier: Development Status :: 3 - Alpha
Requires-Python: >=3.10
Requires-Dist: odoo-addon-fs-base-multi-image<16.1dev,>=16.0dev
Requires-Dist: odoo-addon-image-tag<16.1dev,>=16.0dev
Requires-Dist: odoo<16.1dev,>=16.0a
